sentia/DatasetConcat.py
sentia/__init__.py
sentia/config_sentia.py
sentia/dataset.py
sentia/modeling_sentia.py
sentia/tokenizer.py
sentia/utils/DatasetConcat.py
sentia/utils/MHA.py
sentia/utils/SENTIAFeedForward.py
sentia/utils/__init__.py
sentia/utils/deploy.py
sentia/utils/manual_dataset.py
sentia/utils/text2imagetrain.py
sentia/utils/train.py
sentia-1.17.dist-info/METADATA
sentia-1.17.dist-info/WHEEL
sentia-1.17.dist-info/top_level.txt
sentia-1.17.dist-info/RECORD
