Metadata-Version: 2.1
Name: sentia
Version: 1.17
Summary: A text generation model combining multiple neural network architectures
Home-page: https://github.com/Locutusque/SENTIA.py
Author: Locutusque
Author-email: locutusque.airshipcraft@gmail.com
Classifier: Programming Language :: Python :: 3
Classifier: License :: OSI Approved :: MIT License
Classifier: Operating System :: OS Independent
Requires-Python: >=3.10
Requires-Dist: colorama
Requires-Dist: configparser
Requires-Dist: datasets (>=1.7.0)
Requires-Dist: nltk
Requires-Dist: psutil
Requires-Dist: rotary-embedding-torch
Requires-Dist: sacrebleu
Requires-Dist: torch (>=2.0)
Requires-Dist: tqdm
Requires-Dist: transformers (>=3.0.0)
Requires-Dist: wandb
